CAStatus/__init__.py
CAStatus/log.py
CAStatus/status.py
CAStatus-1.0.0.dist-info/LICENSE
CAStatus-1.0.0.dist-info/METADATA
CAStatus-1.0.0.dist-info/WHEEL
CAStatus-1.0.0.dist-info/top_level.txt
CAStatus-1.0.0.dist-info/RECORD
